scapers_api/__init__.py
scapers_api/request.py
scapers_api/scapers_api.py
scapers_api-0.2.5.dist-info/LICENSE
scapers_api-0.2.5.dist-info/METADATA
scapers_api-0.2.5.dist-info/WHEEL
scapers_api-0.2.5.dist-info/top_level.txt
scapers_api-0.2.5.dist-info/RECORD
