Metadata-Version: 2.1
Name: scapers-api
Version: 0.2.5
Summary: Allows http access to Runescape API Endpoints
Home-page: https://gitlab.com/maximized/scapers_api
Author: Jarod Daming
Author-email: jmdaming@gmail.com
Classifier: Programming Language :: Python :: 3
Classifier: License :: OSI Approved :: MIT License
Classifier: Operating System :: OS Independent
Requires-Python: >=3.9
License-File: LICENSE
Requires-Dist: aiohttp (~=3.8.3)
Requires-Dist: aiolimiter (~=1.0.0)
Requires-Dist: python-semantic-release (==7.32.0)
Requires-Dist: python-dotenv (~=0.21.0)
Requires-Dist: setuptools (==65.4.0)
Requires-Dist: Unidecode (~=1.3.4)
